onetoken/__init__.py
onetoken/account.py
onetoken/autil.py
onetoken/autil_test.py
onetoken/config.py
onetoken/config_test.py
onetoken/conftest.py
onetoken/log_test.py
onetoken/logger.py
onetoken/model.py
onetoken/quote.py
onetoken/quote_test.py
onetoken/rpcutil.py
onetoken/sign_test.py
onetoken/util.py
onetoken/util_test.py
onetoken/websocket_trade_test.py
onetoken-0.2.210201.1.dist-info/METADATA
onetoken-0.2.210201.1.dist-info/WHEEL
onetoken-0.2.210201.1.dist-info/top_level.txt
onetoken-0.2.210201.1.dist-info/RECORD
