Metadata-Version: 2.1
Name: onetoken
Version: 0.2.210201.1
Summary: OneToken Trade System Python SDK
Home-page: https://github.com/1token-trade/onetoken-py-sdk
Author: OneToken
Author-email: admin@1token.trade
License: UNKNOWN
Platform: UNKNOWN
Classifier: Development Status :: 4 - Beta
Classifier: Intended Audience :: Developers
Classifier: Intended Audience :: Financial and Insurance Industry
Classifier: Intended Audience :: Information Technology
Classifier: Topic :: Software Development :: Build Tools
Classifier: Topic :: Office/Business :: Financial :: Investment
Classifier: License :: OSI Approved :: MIT License
Classifier: Programming Language :: Python :: 3
Classifier: Programming Language :: Python :: 3.6
Classifier: Programming Language :: Python :: 3.7
Classifier: Operating System :: OS Independent
Classifier: Environment :: Console
Requires-Python: >=3.6
Requires-Dist: arrow (>=0.12)
Requires-Dist: docopt (>=0.6)
Requires-Dist: PyJWT (>=1.6)
Requires-Dist: PyYAML (>=3)
Requires-Dist: aiohttp (>=3.1)
